{
  "equipment": [
    {
      "id": "1234",
      "line": "Blanking Line-1",
      "equipmentName": "BL-1",
      "equipmentGroup": "Blanking line"
    },
    {
      "id": "1233",
      "line": "Blanking Line-2",
      "equipmentName": "BL-2",
      "equipmentGroup": "Blanking line"
    },
     {
      "id": "1235",
      "line": "Blanking Line-3",
      "equipmentName": "BL-3",
      "equipmentGroup": "Blanking line"
    },
    {
      "id": "12336",
      "line": "Blanking Line-4",
      "equipmentName": "BL-4",
      "equipmentGroup": "Blanking line"
    },
     {
      "id": "12300",
      "line": "Blanking Line-5",
      "equipmentName": "BL-5",
      "equipmentGroup": "Blanking line"
    },
    {
      "id": "12311",
      "line": "Blanking Line-6",
      "equipmentName": "BL-6",
      "equipmentGroup": "Blanking line"
    }
    ,
     {
      "id": "1237",
      "line": "Blanking Line-7",
      "equipmentName": "BL-7",
      "equipmentGroup": "Blanking line"
    },
    {
      "id": "1238",
      "line": "Blanking Line-8",
      "equipmentName": "BL-8",
      "equipmentGroup": "Blanking line"
    }
    ,
     {
      "id": "1239",
      "line": "Blanking Line-9",
      "equipmentName": "BL-9",
      "equipmentGroup": "Blanking line"
    },
    {
      "id": "12310",
      "line": "Blanking Line-10",
      "equipmentName": "BL-10",
      "equipmentGroup": "Blanking line"
    }
  ],
  "model": [
    {
      "id": "1",
      "model": "YTA",
      "description": "YTA"
    },
    {
      "id": "2",
      "model": "YTA/YTB",
      "description": "YTA/YTB"
    },
    {
      "id": "357b",
      "model": "YTB",
      "description": "YTB"
    },
    {
      "id": "8a3c",
      "model": "YTB/YED HB",
      "description": "YTB/YED HB"
    },
    {
      "id": "5004",
      "model": "YTB/YRC",
      "description": "YTB/YRC"
    },
    {
      "id": "f7bb",
      "model": "YED HB",
      "description": "YED HB"
    },
    {
      "id": "3e6f",
      "model": "YED HB/YSD HB",
      "description": "YED HB/YSD HB"
    },
    {
      "id": "c55b",
      "model": "YED HB/YRC",
      "description": "YED HB/YRC"
    },
    {
      "id": "6932",
      "model": "YED HB/YY8",
      "description": "YED HB/YY8"
    },
    {
      "id": "3f99",
      "model": "YSD HB",
      "description": "YSD HB"
    }
  ],
  "shifts": [
    {
      "id": "1",
      "shift": "A",
      "start": "06:30:00",
      "end": "15:14:59"
    },
    {
      "id": "2",
      "shift": "B",
      "start": "15:15:00",
      "end": "23:59:59"
    },
    {
      "id": "3",
      "shift": "C",
      "start": "00:00:00",
      "end": "06:29:59"
    }
  ],
  "variant": [
    {
      "id": "1",
      "variant": "R00",
      "commonName": "R00"
    },
    {
      "id": "be2a",
      "variant": "R01",
      "commonName": "R01"
    },
    {
      "id": "1a86",
      "variant": "R02",
      "commonName": "R02"
    },
    {
      "id": "1423",
      "variant": "R10",
      "commonName": "R10"
    },
    {
      "id": "3206",
      "variant": "T10",
      "commonName": "T10"
    },
    {
      "id": "705c",
      "variant": "P10",
      "commonName": "P10"
    }
  ],
  "breaks": [
    {
      "id": "1",
      "start": "8:40:00",
      "end": "8:47:30"
    },
    {
      "id": "2",
      "start": "10:45:00",
      "end": "11:15:00"
    },
    {
      "id": "3",
      "start": " 13:25:00",
      "end": " 13:32:30 "
    },
    {
      "id": "4",
      "start": " 17:25:00",
      "end": " 17:32:30 "
    },
    {
      "id": "5",
      "start": " 20:00:00",
      "end": " 20:30:00 "
    }
  ],
  "recipes": [
    {
      "id": "1",
      "equipmentId": "BL-2",
      "dieNumber": "101",
      "model": "YTB",
      "partDescription": "YTB MAIN FLOOR R/L (CR)",
      "variant": "TRUE",
      "coilCode": "I1167020XF6",
      "outputDescription": "BLANK,MAIN FLOOR,R/L",
      "thicknessNominal": "0.55",
      "thicknessUpper": "0.575",
      "thicknessLower": "0.525",
      "thicknessUnit": "mm",
      "feedLength": "1123",
      "feedLengthUnit": "mm",
      "widthNominal": "1528",
      "widthUnit": "mm"
    },
    {
      "id": "2",
      "equipmentId": "BL-2",
      "dieNumber": "102",
      "model": "YTB",
      "partDescription": "YTB FENDER RH (CR)",
      "variant": "TRUE",
      "coilCode": "I1167020XH6",
      "outputDescription": "BLANK,FRONT FENDER,R",
      "thicknessNominal": "0.7",
      "thicknessUpper": "0.725",
      "thicknessLower": "0.675",
      "thicknessUnit": "mm",
      "feedLength": "1049",
      "feedLengthUnit": "mm",
      "widthNominal": "935",
      "widthUnit": "mm"
    },
    {
      "id": "3",
      "equipmentId": "BL-2",
      "dieNumber": "103",
      "model": "YTB",
      "partDescription": "YTB FENDER LH (CR)",
      "variant": "TRUE",
      "coilCode": "I1167020XH6",
      "outputDescription": "BLANK,FRONT FENDER,L",
      "thicknessNominal": "0.7",
      "thicknessUpper": "0.725",
      "thicknessLower": "0.675",
      "thicknessUnit": "mm",
      "feedLength": "1049",
      "feedLengthUnit": "mm",
      "widthNominal": "935",
      "widthUnit": "mm"
    },
    {
      "id": "2ec1",
      "equipmentId": "BL-2",
      "dieNumber": 104,
      "model": "YTB",
      "partDescription": "YTB BDI (CR)",
      "variant": "TRUE",
      "coilCode": "I1167020WX6",
      "outputDescription": "BLANK,BACK DOOR INNER",
      "thicknessNominal": null,
      "thicknessUpper": null,
      "thicknessLower": null,
      "thicknessUnit": null,
      "feedLength": null,
      "feedLengthUnit": null,
      "widthNominal": null,
      "widthUnit": null
    },
    {
      "id": "2492",
      "equipmentId": "BL-2",
      "dieNumber": 401,
      "model": "YTB",
      "partDescription": "YTB MAIN FLOOR R/L (GA)",
      "variant": "TRUE",
      "coilCode": "I1167020YV6",
      "outputDescription": "BLANK,MAIN FLOOR,R/L",
      "thicknessNominal": null,
      "thicknessUpper": null,
      "thicknessLower": null,
      "thicknessUnit": null,
      "feedLength": null,
      "feedLengthUnit": null,
      "widthNominal": null,
      "widthUnit": null
    }
  ]
}